drone/__init__.py
drone/drone.py
lfedu-0.0.1.dist-info/METADATA
lfedu-0.0.1.dist-info/WHEEL
lfedu-0.0.1.dist-info/top_level.txt
lfedu-0.0.1.dist-info/RECORD
