Metadata-Version: 2.1
Name: lfedu
Version: 0.0.1
Summary: Program the drone operating library
Author: cangyun
Author-email: 4uansi@gmail.com
Classifier: Programming Language :: Python :: 3
Classifier: License :: OSI Approved :: MIT License
Classifier: Operating System :: OS Independent
Requires-Python: >=3.6
